scherbelberg/__init__.py
scherbelberg/_cli/__init__.py
scherbelberg/_cli/_main_.py
scherbelberg/_cli/catalog.py
scherbelberg/_cli/create.py
scherbelberg/_cli/destroy.py
scherbelberg/_cli/ls.py
scherbelberg/_cli/nuke.py
scherbelberg/_cli/scp.py
scherbelberg/_cli/ssh.py
scherbelberg/_core/__init__.py
scherbelberg/_core/abc.py
scherbelberg/_core/catalog.py
scherbelberg/_core/cluster.py
scherbelberg/_core/command.py
scherbelberg/_core/const.py
scherbelberg/_core/creator.py
scherbelberg/_core/debug.py
scherbelberg/_core/log.py
scherbelberg/_core/node.py
scherbelberg/_core/process.py
scherbelberg/_core/sshconfig.py
scherbelberg/_core/ssl.py
scherbelberg/share/bootstrap_01.sh
scherbelberg/share/bootstrap_02.sh
scherbelberg/share/bootstrap_03.sh
scherbelberg/share/bootstrap_scheduler.sh
scherbelberg/share/bootstrap_worker.sh
scherbelberg/share/requirements_conda.txt
scherbelberg/share/sshd_config.patch
scherbelberg-0.0.6.dist-info/LICENSE
scherbelberg-0.0.6.dist-info/METADATA
scherbelberg-0.0.6.dist-info/WHEEL
scherbelberg-0.0.6.dist-info/entry_points.txt
scherbelberg-0.0.6.dist-info/top_level.txt
scherbelberg-0.0.6.dist-info/RECORD
