Metadata-Version: 2.1
Name: scherbelberg
Version: 0.0.6
Summary: HPC cluster deployment and management for the Hetzner Cloud
Home-page: https://github.com/pleiszenburg/scherbelberg
Author: Sebastian M. Ernst
Author-email: ernst@pleiszenburg.de
License: BSD
Download-URL: https://github.com/pleiszenburg/scherbelberg/archive/v0.0.6.tar.gz
Keywords: HPC,cluster,dask
Platform: UNKNOWN
Classifier: Development Status :: 3 - Alpha
Classifier: Environment :: Console
Classifier: Intended Audience :: Developers
Classifier: Intended Audience :: Education
Classifier: Intended Audience :: Information Technology
Classifier: Intended Audience :: Science/Research
Classifier: Intended Audience :: System Administrators
Classifier: License :: OSI Approved :: BSD License
Classifier: Operating System :: MacOS
Classifier: Operating System :: POSIX :: BSD
Classifier: Operating System :: POSIX :: Linux
Classifier: Programming Language :: Python :: 3
Classifier: Programming Language :: Python :: 3.8
Classifier: Programming Language :: Python :: 3.9
Classifier: Programming Language :: Python :: 3.10
Classifier: Programming Language :: Python :: 3 :: Only
Classifier: Programming Language :: Python :: Implementation :: CPython
Classifier: Topic :: System :: Clustering
Classifier: Topic :: Scientific/Engineering
Classifier: Topic :: System
Classifier: Topic :: System :: Systems Administration
Classifier: Topic :: Utilities
Requires-Python: >=3.8
License-File: LICENSE
Requires-Dist: click
Requires-Dist: dask
Requires-Dist: hcloud
Requires-Dist: pyyaml
Requires-Dist: tabulate
Requires-Dist: typeguard
Provides-Extra: all
Requires-Dist: dask ; extra == 'all'
Requires-Dist: sphinx-rtd-theme ; extra == 'all'
Requires-Dist: black ; extra == 'all'
Requires-Dist: sphinx-click ; extra == 'all'
Requires-Dist: setuptools ; extra == 'all'
Requires-Dist: sphinx-autodoc-typehints ; extra == 'all'
Requires-Dist: twine ; extra == 'all'
Requires-Dist: click ; extra == 'all'
Requires-Dist: tabulate ; extra == 'all'
Requires-Dist: sphinx ; extra == 'all'
Requires-Dist: typeguard ; extra == 'all'
Requires-Dist: wheel ; extra == 'all'
Requires-Dist: python-lsp-server[all] ; extra == 'all'
Requires-Dist: hcloud ; extra == 'all'
Requires-Dist: myst-parser ; extra == 'all'
Requires-Dist: pyyaml ; extra == 'all'
Provides-Extra: base
Requires-Dist: click ; extra == 'base'
Requires-Dist: dask ; extra == 'base'
Requires-Dist: hcloud ; extra == 'base'
Requires-Dist: pyyaml ; extra == 'base'
Requires-Dist: tabulate ; extra == 'base'
Requires-Dist: typeguard ; extra == 'base'
Provides-Extra: dev
Requires-Dist: black ; extra == 'dev'
Requires-Dist: myst-parser ; extra == 'dev'
Requires-Dist: python-lsp-server[all] ; extra == 'dev'
Requires-Dist: setuptools ; extra == 'dev'
Requires-Dist: sphinx ; extra == 'dev'
Requires-Dist: sphinx-click ; extra == 'dev'
Requires-Dist: sphinx-rtd-theme ; extra == 'dev'
Requires-Dist: sphinx-autodoc-typehints ; extra == 'dev'
Requires-Dist: twine ; extra == 'dev'
Requires-Dist: wheel ; extra == 'dev'
